neoDNS/__init__.py
neoDNS/db.py
neoDNS/main.py
neoDNS/schema.sql
neoDNS-0.2.1.dist-info/METADATA
neoDNS-0.2.1.dist-info/WHEEL
neoDNS-0.2.1.dist-info/top_level.txt
neoDNS-0.2.1.dist-info/RECORD
