Metadata-Version: 2.1
Name: neoDNS
Version: 0.2.1
Summary: lightweight 'dns' server
Author-email: Ryan Huang <ryan@alien.gov>
Project-URL: Homepage, https://github.com/JuanCldCmt/neoDNS
Project-URL: Bug Tracker, https://github.com/JuanCldCmt/neoDNS
Classifier: Programming Language :: Python :: 3
Classifier: License :: OSI Approved :: MIT License
Classifier: Operating System :: OS Independent
Requires-Dist: flask
Requires-Dist: Werkzeug
